bungio/__init__.py
bungio/client.py
bungio/definitions.py
bungio/error.py
bungio/manifest.py
bungio/singleton.py
bungio/utils.py
bungio/api/__init__.py
bungio/api/client.py
bungio/api/bungie/__init__.py
bungio/api/bungie/app.py
bungio/api/bungie/community_content.py
bungio/api/bungie/content.py
bungio/api/bungie/destiny2.py
bungio/api/bungie/fireteam.py
bungio/api/bungie/fireteam_finder.py
bungio/api/bungie/forum.py
bungio/api/bungie/get_available_locales.py
bungio/api/bungie/global_alerts.py
bungio/api/bungie/group_v2.py
bungio/api/bungie/settings.py
bungio/api/bungie/social.py
bungio/api/bungie/tokens.py
bungio/api/bungie/trending.py
bungio/api/bungie/user.py
bungio/api/bungie/user_system_overrides.py
bungio/api/overwrites/__init__.py
bungio/api/overwrites/destiny2.py
bungio/http/__init__.py
bungio/http/auth.py
bungio/http/client.py
bungio/http/ratelimiting.py
bungio/http/route.py
bungio/http/routes/__init__.py
bungio/http/routes/app.py
bungio/http/routes/community_content.py
bungio/http/routes/content.py
bungio/http/routes/destiny2.py
bungio/http/routes/fireteam.py
bungio/http/routes/fireteam_finder.py
bungio/http/routes/forum.py
bungio/http/routes/get_available_locales.py
bungio/http/routes/global_alerts.py
bungio/http/routes/group_v2.py
bungio/http/routes/settings.py
bungio/http/routes/social.py
bungio/http/routes/tokens.py
bungio/http/routes/trending.py
bungio/http/routes/user.py
bungio/http/routes/user_system_overrides.py
bungio/models/__init__.py
bungio/models/auth.py
bungio/models/base.py
bungio/models/enums.py
bungio/models/basic/__init__.py
bungio/models/basic/character.py
bungio/models/basic/clan.py
bungio/models/basic/user.py
bungio/models/bungie/__init__.py
bungio/models/bungie/applications.py
bungio/models/bungie/components.py
bungio/models/bungie/dates.py
bungio/models/bungie/entities.py
bungio/models/bungie/exceptions.py
bungio/models/bungie/fireteam.py
bungio/models/bungie/fireteamfinder.py
bungio/models/bungie/forum.py
bungio-1.7.0.dist-info/licenses/LICENSE
bungio-1.7.0.dist-info/METADATA
bungio-1.7.0.dist-info/WHEEL
bungio-1.7.0.dist-info/top_level.txt
bungio-1.7.0.dist-info/RECORD
