Metadata-Version: 2.4
Name: bungio
Version: 1.7.0
Summary: A destiny 2 / bungie api wrapper
Author: Daniel J
License: MIT License
Project-URL: Repository, https://github.com/Kigstn/BungIO
Project-URL: Documentation, https://bungio.readthedocs.io/en/latest/
Keywords: asyncio,destiny,destiny 2,bungie,api
Requires-Python: >=3.10
License-File: LICENSE
Requires-Dist: aiohttp~=3.8
Requires-Dist: attrs~=22.1
Requires-Dist: sqlalchemy[aiosqlite]~=1.4
Provides-Extra: speedups
Requires-Dist: orjson~=3.6; extra == "speedups"
Requires-Dist: brotli~=1.0; extra == "speedups"
Requires-Dist: charset-normalizer~=3.3; extra == "speedups"
Provides-Extra: cache
Requires-Dist: aiohttp-client-cache~=0.7; extra == "cache"
Provides-Extra: docs
Requires-Dist: mkdocstrings[python]~=0.25; extra == "docs"
Requires-Dist: mkdocs-material~=9.5; extra == "docs"
Requires-Dist: mkdocs-awesome-pages-plugin~=2.9; extra == "docs"
Requires-Dist: mkdocs-autorefs~=1.0; extra == "docs"
Requires-Dist: mkdocs~=1.6; extra == "docs"
Provides-Extra: test
Requires-Dist: pytest~=7.1; extra == "test"
Requires-Dist: pytest-asyncio~=0.18; extra == "test"
Provides-Extra: dev
Requires-Dist: ruff~=0.5; extra == "dev"
Requires-Dist: pre-commit~=3.7; extra == "dev"
Dynamic: license-file
